django_perfect_breadcrumbs/__init__.py
django_perfect_breadcrumbs/apps.py
django_perfect_breadcrumbs/builder.py
django_perfect_breadcrumbs/context_processors.py
django_perfect_breadcrumbs/middleware.py
django_perfect_breadcrumbs/settings.py
django_perfect_breadcrumbs-0.1.0.dist-info/LICENSE
django_perfect_breadcrumbs-0.1.0.dist-info/METADATA
django_perfect_breadcrumbs-0.1.0.dist-info/WHEEL
django_perfect_breadcrumbs-0.1.0.dist-info/RECORD
