Metadata-Version: 2.1
Name: django-perfect-breadcrumbs
Version: 0.1.0
Summary: 
Author: Josh Karamuth
Author-email: hello@joshkaramuth.com
Requires-Python: >=3.11,<4.0
Classifier: Programming Language :: Python :: 3
Classifier: Programming Language :: Python :: 3.11
Requires-Dist: django (>=4.2.3,<5.0.0)
